humioapi/__init__.py
humioapi/api.py
humioapi/exceptions.py
humioapi/loadenv.py
humioapi/logsetup.py
humioapi/monkeypatch.py
humioapi/queries.py
humioapi/timeseries.py
humioapi/utils.py
humioapi-0.11.0.dist-info/LICENSE
humioapi-0.11.0.dist-info/WHEEL
humioapi-0.11.0.dist-info/METADATA
humioapi-0.11.0.dist-info/RECORD
