Metadata-Version: 2.1
Name: humioapi
Version: 0.11.0
Summary: An unofficial Python library wrapping the official humiolib to provide extra helpers and utility functions
Home-page: https://github.com/gwtwod/humioapi
Author: Jostein Haukeli
Requires-Python: >=3.8
Classifier: Programming Language :: Python :: 3
Classifier: Programming Language :: Python :: 3.10
Classifier: Programming Language :: Python :: 3.8
Classifier: Programming Language :: Python :: 3.9
Provides-Extra: pandas
Requires-Dist: chardet (>=4)
Requires-Dist: colorama (>=0.4.4)
Requires-Dist: humiolib (>=0.2.4,<0.3.0)
Requires-Dist: pandas (>=1.2); extra == "pandas"
Requires-Dist: pendulum (>=2.1.2)
Requires-Dist: python-dotenv (>=0.15)
Requires-Dist: snaptime (>=0.2.4)
Requires-Dist: structlog (>=20.2)
Requires-Dist: tqdm (>=4.62.3)
Requires-Dist: tzlocal (>=2.1)
Project-URL: Repository, https://github.com/gwtwod/humioapi
